{
  "skills": [
    {
      "skill": "Problem Solving",
      "indent": 0,
      "children": []
    },
    {
      "skill": "Programming Languages",
      "indent": 0,
      "children": []
    },
    {
      "skill": "Data Structures",
      "indent": 0,
      "children": [
        "Designed and implemented efficient data structures for a real-time gaming server",
        "Optimized memory usage in a resource-constrained environment"
      ]
    },
    {
      "skill": "Web Development",
      "indent": 0,
      "children": [
        "Developed responsive web applications using HTML5, CSS3, and JavaScript",
        "Integrated RESTful APIs for dynamic content"
      ]
    },
    {
      "skill": "Machine Learning",
      "indent": 0,
      "children": [
        "Built a recommendation system using collaborative filtering techniques",
        "Trained deep learning models for image classification tasks"
      ]
    },
    {
      "skill": "Database Management",
      "indent": 0,
      "children": [
        "Designed and optimized relational database schemas for e-commerce platforms",
        "Implemented database replication for high availability and fault tolerance"
      ]
    },
    {
      "skill": "Cybersecurity",
      "indent": 0,
      "children": [
        "Conducted penetration testing to identify vulnerabilities in web applications",
        "Developed a secure authentication system with multi-factor authentication (MFA)"
      ]
    },
    {
      "skill": "Cloud Computing",
      "indent": 0,
      "children": [
        "Deployed scalable applications on AWS cloud infrastructure",
        "Managed containerized applications with Kubernetes"
      ]
    }
  ]
}
